{
  "ver": "1.0",
  "ret": true,
  "errcode": 0,
  "errmsg": "",
  "data": [
    {
      "id": 20,
      "spaceType": "轰趴馆",
      "spaceName": "谜墓诡窟密室",
      "spaceCounty": "丰台区",
      "address1": "丰台区马连道卫强校甲40号中都雅润B1层",
      "address2": "马连道卫强校甲40号中都雅润B1层",
      "lat": 39.879319,
      "lng": 116.334733
    },
    {
      "id": 21,
      "spaceType": "轰趴馆",
      "spaceName": "朋派乐活",
      "spaceCounty": "丰台区",
      "address1": "丰台区马连道中里三区4号楼北侧入口地下一层",
      "address2": "马连道中里三区4号楼北侧入口地下一层",
      "lat": 39.890999,
      "lng": 116.337642
    },
    {
      "id": 22,
      "spaceType": "咖啡馆",
      "spaceName": "茶咖包间",
      "spaceCounty": "丰台区",
      "address1": "丰台区马家堡东路七克拉东门院内7号楼16层",
      "address2": "马家堡东路七克拉东门院内7号楼16层",
      "lat": 39.845671,
      "lng": 116.391753
    },
    {
      "id": 23,
      "spaceType": "轰趴馆",
      "spaceName": "朋友圈轰趴馆",
      "spaceCounty": "丰台区",
      "address1": "丰台区马家堡东路121号7克拉2号楼219室",
      "address2": "马家堡东路121号7克拉2号楼219室",
      "lat": 39.845671,
      "lng": 116.391753
    },
    {
      "id": 24,
      "spaceType": "舞蹈室",
      "spaceName": "928舞蹈工作室",
      "spaceCounty": "丰台区",
      "address1": "丰台区马家堡东路106号自然新天地928、901室",
      "address2": "马家堡东路106号自然新天地928、901室",
      "lat": 39.847797,
      "lng": 116.394563
    },
    {
      "id": 25,
      "spaceType": "轰趴馆",
      "spaceName": "爱聚屋",
      "spaceCounty": "丰台区",
      "address1": "丰台区马家堡路180号蓝光云鼎912",
      "address2": "马家堡路180号蓝光云鼎912",
      "lat": 39.841382,
      "lng": 116.385769
    },
    {
      "id": 26,
      "spaceType": "肚皮舞培训室",
      "spaceName": "格洛莉雅舞蹈培训中心",
      "spaceCounty": "丰台区",
      "address1": "丰台区马家堡西路15号时代风帆大厦2区1902",
      "address2": "马家堡西路15号时代风帆大厦2区1902",
      "lat": 39.852702,
      "lng": 116.376507
    },
    {
      "id": 27,
      "spaceType": "溜冰场",
      "spaceName": "风采轮滑培训俱乐部",
      "spaceCounty": "丰台区",
      "address1": "丰台区开阳里小区",
      "address2": "开阳里小区",
      "lat": 39.871396,
      "lng": 116.375732
    },
    {
      "id": 28,
      "spaceType": "足球馆",
      "spaceName": "紫谷庄园足球俱乐部",
      "spaceCounty": "丰台区",
      "address1": "丰台区卢沟桥农场路紫谷庄园足球场",
      "address2": "卢沟桥农场路紫谷庄园足球场",
      "lat": 39.838747,
      "lng": 116.242823
    },
    {
      "id": 29,
      "spaceType": "轰趴馆",
      "spaceName": "对门轰趴馆",
      "spaceCounty": "丰台区",
      "address1": "丰台区刘家窑方群公寓C座801室",
      "address2": "刘家窑方群公寓C座801室",
      "lat": 39.866428,
      "lng": 116.420749
    },
    {
      "id": 30,
      "spaceType": "花店",
      "spaceName": "花悦",
      "spaceCounty": "丰台区",
      "address1": "丰台区丰桥路三环新城6号院3号楼甲3-56号",
      "address2": "丰桥路三环新城6号院3号楼甲3-56号",
      "lat": 39.85682,
      "lng": 116.315759
    },
    {
      "id": 31,
      "spaceType": "花店",
      "spaceName": "唯爱(北京二十一店)",
      "spaceCounty": "丰台区",
      "address1": "丰台区丰台路口西四环南路19号花之恋鲜花店",
      "address2": "丰台路口西四环南路19号花之恋鲜花店",
      "lat": 39.872982,
      "lng": 116.299004
    },
    {
      "id": 32,
      "spaceType": "花店",
      "spaceName": "万宁花语鲜花(看丹桥店)",
      "spaceCounty": "丰台区",
      "address1": "丰台区丰台南路120号",
      "address2": "丰台南路120号",
      "lat": 39.847141,
      "lng": 116.294758
    },
    {
      "id": 33,
      "spaceType": "花店",
      "spaceName": "花千束品牌鲜花馆",
      "spaceCounty": "丰台区",
      "address1": "丰台区东大街西里",
      "address2": "东大街西里",
      "lat": 39.867908,
      "lng": 116.297392
    },
    {
      "id": 34,
      "spaceType": "舞蹈室",
      "spaceName": "m.t舞蹈工作室",
      "spaceCounty": "丰台区",
      "address1": "丰台区东大街嘉城广场D座3号楼605 M.T舞蹈工作室",
      "address2": "东大街嘉城广场D座3号楼605 M.T舞蹈工作室",
      "lat": 39.86305,
      "lng": 116.29906
    },
    {
      "id": 35,
      "spaceType": "轰趴馆",
      "spaceName": "房车轰趴馆",
      "spaceCounty": "丰台区",
      "address1": "丰台区东三环南路98号高和蓝峰大厦1层",
      "address2": "东三环南路98号高和蓝峰大厦1层",
      "lat": 39.871307,
      "lng": 116.468534
    },
    {
      "id": 36,
      "spaceType": "花店",
      "spaceName": "四季百盛花房",
      "spaceCounty": "丰台区",
      "address1": "丰台区槐房西路316号院",
      "address2": "槐房西路316号院",
      "lat": 39.812545,
      "lng": 116.375937
    },
    {
      "id": 37,
      "spaceType": "肚皮舞培训室",
      "spaceName": "舞拳拳击工作室",
      "spaceCounty": "丰台区",
      "address1": "丰台区怡海花园恒泰园10号楼105",
      "address2": "怡海花园恒泰园10号楼105",
      "lat": 39.840629,
      "lng": 116.306751
    },
    {
      "id": 38,
      "spaceType": "私人影院",
      "spaceName": "森森私家影院",
      "spaceCounty": "丰台区",
      "address1": "丰台区六里桥北京西站太平桥东里",
      "address2": "六里桥北京西站太平桥东里",
      "lat": 39.903473,
      "lng": 116.327694
    },
    {
      "id": 39,
      "spaceType": "私人影院",
      "spaceName": "疯狂影酷(北京银座和谐广场店)",
      "spaceCounty": "丰台区",
      "address1": "丰台区六里桥/丽泽桥六里桥莲宝中路银座和谐广场5",
      "address2": "六里桥/丽泽桥六里桥莲宝中路银座和谐广场5",
      "lat": 39.887809,
      "lng": 116.304566
    },
    {
      "id": 40,
      "spaceType": "私人影院",
      "spaceName": "漫步情侣",
      "spaceCounty": "丰台区",
      "address1": "丰台区洋桥/木樨园永定门外大街101-2号附近",
      "address2": "洋桥/木樨园永定门外大街101-2号附近",
      "lat": 39.867094,
      "lng": 116.415909
    },
    {
      "id": 41,
      "spaceType": "足球馆",
      "spaceName": "万芳亭公园足球场",
      "spaceCounty": "丰台区",
      "address1": "丰台区木樨园洋桥西里甲2号万芳亭公园内",
      "address2": "木樨园洋桥西里甲2号万芳亭公园内",
      "lat": 39.864794,
      "lng": 116.382489
    },
    {
      "id": 42,
      "spaceType": "溜冰场",
      "spaceName": "奥康店",
      "spaceCounty": "丰台区",
      "address1": "丰台区木樨园京温服装市场二期4168",
      "address2": "木樨园京温服装市场二期4168",
      "lat": 39.855942,
      "lng": 116.40607
    },
    {
      "id": 43,
      "spaceType": "网球场",
      "spaceName": "得乐网球培训",
      "spaceCounty": "丰台区",
      "address1": "丰台区田各庄路321号",
      "address2": "田各庄路321号",
      "lat": 39.87845,
      "lng": 116.274687
    },
    {
      "id": 44,
      "spaceType": "别墅",
      "spaceName": "罗马假日欧式精装",
      "spaceCounty": "丰台区",
      "address1": "丰台区泉湖东路青龙湖旁高档别墅区",
      "address2": "泉湖东路青龙湖旁高档别墅区",
      "lat": 39.793886,
      "lng": 116.088129
    },
    {
      "id": 45,
      "spaceType": "别墅",
      "spaceName": "龙湖景区独栋别墅",
      "spaceCounty": "丰台区",
      "address1": "丰台区王佐乡羊圈头村",
      "address2": "王佐乡羊圈头村",
      "lat": 39.84747,
      "lng": 116.088999
    },
    {
      "id": 46,
      "spaceType": "足球馆",
      "spaceName": "爱踢客青少年足球俱乐部",
      "spaceCounty": "丰台区",
      "address1": "丰台区北京西站/六里桥岳各庄东路万丰公园足球场",
      "address2": "北京西站/六里桥岳各庄东路万丰公园足球场",
      "lat": 39.889811,
      "lng": 116.299903
    },
    {
      "id": 47,
      "spaceType": "轰趴馆",
      "spaceName": "绘心乐活馆",
      "spaceCounty": "丰台区",
      "address1": "丰台区方庄南路58号院晶城秀府12号楼207室",
      "address2": "方庄南路58号院晶城秀府12号楼207室",
      "lat": 39.8527,
      "lng": 116.446749
    },
    {
      "id": 48,
      "spaceType": "溜冰场",
      "spaceName": "飞速轮滑培训班",
      "spaceCounty": "丰台区",
      "address1": "丰台区方庄体育公园",
      "address2": "方庄体育公园",
      "lat": 39.87305,
      "lng": 116.434687
    },
    {
      "id": 49,
      "spaceType": "足球馆",
      "spaceName": "颐方会馆-足球场",
      "spaceCounty": "丰台区",
      "address1": "丰台区方庄成寿寺路甲12号",
      "address2": "方庄成寿寺路甲12号",
      "lat": 39.85957,
      "lng": 116.454511
    },
    {
      "id": 50,
      "spaceType": "私人影院",
      "spaceName": "万达影城",
      "spaceCounty": "丰台区",
      "address1": "丰台区分钟寺/成寿寺万达广场西门金街",
      "address2": "分钟寺/成寿寺万达广场西门金街",
      "lat": 39.859682,
      "lng": 116.455575
    },
    {
      "id": 51,
      "spaceType": "轰趴馆",
      "spaceName": "樂未央百人轰趴馆",
      "spaceCounty": "丰台区",
      "address1": "丰台区南四环西路188号总部基地17区",
      "address2": "南四环西路188号总部基地17区",
      "lat": 39.829292,
      "lng": 116.298718
    },
    {
      "id": 52,
      "spaceType": "花店",
      "spaceName": "九州花语轩",
      "spaceCounty": "丰台区",
      "address1": "丰台区南四环西路178",
      "address2": "南四环西路178",
      "lat": 39.835737,
      "lng": 116.300049
    },
    {
      "id": 53,
      "spaceType": "足球馆",
      "spaceName": "gogo泡泡足球俱乐部",
      "spaceCounty": "丰台区",
      "address1": "丰台区南四环西路128号院4号楼12层1515-1516室",
      "address2": "南四环西路128号院4号楼12层1515-1516室",
      "lat": 39.835436,
      "lng": 116.304898
    },
    {
      "id": 54,
      "spaceType": "轰趴馆",
      "spaceName": "全友聚会轰趴馆",
      "spaceCounty": "丰台区",
      "address1": "丰台区南三环中路70号南曦大厦底商华夏金融会所三层",
      "address2": "南三环中路70号南曦大厦底商华夏金融会所三层",
      "lat": 39.862612,
      "lng": 116.408355
    },
    {
      "id": 55,
      "spaceType": "轰趴馆",
      "spaceName": "聚齐发小儿Club",
      "spaceCounty": "丰台区",
      "address1": "丰台区南苑团河路民俗旅游文化街西37号",
      "address2": "南苑团河路民俗旅游文化街西37号",
      "lat": 39.801449,
      "lng": 116.384038
    },
    {
      "id": 56,
      "spaceType": "足球馆",
      "spaceName": "舒华五人制足球场",
      "spaceCounty": "丰台区",
      "address1": "丰台区大红门路舒华五人制足球场",
      "address2": "大红门路舒华五人制足球场",
      "lat": 39.850063,
      "lng": 116.413873
    },
    {
      "id": 57,
      "spaceType": "私人影院",
      "spaceName": "家庭影院体验厅",
      "spaceCounty": "丰台区",
      "address1": "丰台区草桥西路草桥欣园4区附近",
      "address2": "草桥西路草桥欣园4区附近",
      "lat": 39.850829,
      "lng": 116.357615
    },
    {
      "id": 58,
      "spaceType": "溜冰场",
      "spaceName": "龙城旱冰场",
      "spaceCounty": "丰台区",
      "address1": "丰台区草桥右外斜街与中顶村路交汇北侧",
      "address2": "草桥右外斜街与中顶村路交汇北侧",
      "lat": 39.862456,
      "lng": 116.365127
    },
    {
      "id": 59,
      "spaceType": "肚皮舞培训室",
      "spaceName": "纳兰舞社",
      "spaceCounty": "丰台区",
      "address1": "丰台区宋庄路71号扑满山大厦3号楼1202室",
      "address2": "宋庄路71号扑满山大厦3号楼1202室",
      "lat": 39.85143,
      "lng": 116.433849
    },
    {
      "id": 60,
      "spaceType": "私人影院",
      "spaceName": "云乐迪私影汇",
      "spaceCounty": "丰台区",
      "address1": "丰台区宋庄路71号扑满山2层",
      "address2": "宋庄路71号扑满山2层",
      "lat": 39.851196,
      "lng": 116.43406
    },
    {
      "id": 61,
      "spaceType": "花店",
      "spaceName": "爱慕鲜花(开心花坊鲜花婚庆",
      "spaceCounty": "丰台区",
      "address1": "丰台区宋庄路18号开心花坊鲜花婚庆",
      "address2": "宋庄路18号开心花坊鲜花婚庆",
      "lat": 39.85651,
      "lng": 116.435199
    },
    {
      "id": 62,
      "spaceType": "足球馆",
      "spaceName": "华夏醒狮足球俱乐部",
      "spaceCounty": "丰台区",
      "address1": "丰台区青塔卢沟桥",
      "address2": "青塔卢沟桥",
      "lat": 39.903675,
      "lng": 116.274817
    },
    {
      "id": 63,
      "spaceType": "花店",
      "spaceName": "兰景丽园鲜花(青塔店)",
      "spaceCounty": "丰台区",
      "address1": "丰台区青塔西路1号",
      "address2": "青塔西路1号",
      "lat": 39.900983,
      "lng": 116.270697
    },
    {
      "id": 64,
      "spaceType": "肚皮舞培训室",
      "spaceName": "英姿东方舞",
      "spaceCounty": "丰台区",
      "address1": "丰台区成寿寺路甲12号",
      "address2": "成寿寺路甲12号",
      "lat": 39.85957,
      "lng": 116.454511
    },
    {
      "id": 65,
      "spaceType": "私人影院",
      "spaceName": "第六感影吧西餐厅",
      "spaceCounty": "丰台区",
      "address1": "丰台区新发地银地家园B区",
      "address2": "新发地银地家园B区",
      "lat": 39.825162,
      "lng": 116.337974
    },
    {
      "id": 66,
      "spaceType": "花店",
      "spaceName": "小怪兽的花",
      "spaceCounty": "丰台区",
      "address1": "丰台区城南嘉园",
      "address2": "城南嘉园",
      "lat": 39.841811,
      "lng": 116.375941
    },
    {
      "id": 67,
      "spaceType": "花店",
      "spaceName": "唯爱花艺(丰台店)",
      "spaceCounty": "丰台区",
      "address1": "丰台区七里庄丰台东大街5号院社区",
      "address2": "七里庄丰台东大街5号院社区",
      "lat": 39.868291,
      "lng": 116.30401
    },
    {
      "id": 68,
      "spaceType": "私人影院",
      "spaceName": "天际影视",
      "spaceCounty": "丰台区",
      "address1": "丰台区旧宫南苑路和义东里京都酒厂院内7号楼",
      "address2": "旧宫南苑路和义东里京都酒厂院内7号楼",
      "lat": 39.820011,
      "lng": 116.41273
    },
    {
      "id": 69,
      "spaceType": "足球馆",
      "spaceName": "北京银潮足球俱乐部",
      "spaceCounty": "丰台区",
      "address1": "丰台区蒲方路芳星园二区11层",
      "address2": "蒲方路芳星园二区11层",
      "lat": 39.870452,
      "lng": 116.44176
    },
    {
      "id": 70,
      "spaceType": "足球馆",
      "spaceName": "国际米兰足球青训",
      "spaceCounty": "丰台区",
      "address1": "丰台区花乡南四环西路129号北京八中怡海分校",
      "address2": "花乡南四环西路129号北京八中怡海分校",
      "lat": 39.840462,
      "lng": 116.308939
    },
    {
      "id": 71,
      "spaceType": "足球馆",
      "spaceName": "南宫体育公园足球训练营",
      "spaceCounty": "丰台区",
      "address1": "丰台区云岗南宫滨河路",
      "address2": "云岗南宫滨河路",
      "lat": 39.80697,
      "lng": 116.150553
    },
    {
      "id": 72,
      "spaceType": "肚皮舞培训室",
      "spaceName": "传雅体育发展有限公司",
      "spaceCounty": "丰台区",
      "address1": "丰台区云岗南宫路8号院6号楼28号",
      "address2": "云岗南宫路8号院6号楼28号",
      "lat": 39.810595,
      "lng": 116.164408
    }
  ]
}